odoo8_addon_crm_lead_code-8.0.1.0.0.99.dev17-py3.8-nspkg.pth
odoo_addons/crm_lead_code/README.rst
odoo_addons/crm_lead_code/__init__.py
odoo_addons/crm_lead_code/__openerp__.py
odoo_addons/crm_lead_code/data/lead_sequence.xml
odoo_addons/crm_lead_code/i18n/bg.po
odoo_addons/crm_lead_code/i18n/crm_lead_code.pot
odoo_addons/crm_lead_code/i18n/de.po
odoo_addons/crm_lead_code/i18n/es.po
odoo_addons/crm_lead_code/i18n/fr.po
odoo_addons/crm_lead_code/i18n/hr.po
odoo_addons/crm_lead_code/i18n/it.po
odoo_addons/crm_lead_code/i18n/pt_BR.po
odoo_addons/crm_lead_code/i18n/sk.po
odoo_addons/crm_lead_code/i18n/sl.po
odoo_addons/crm_lead_code/i18n/zh_CN.po
odoo_addons/crm_lead_code/models/__init__.py
odoo_addons/crm_lead_code/models/crm_lead.py
odoo_addons/crm_lead_code/static/description/icon.png
odoo_addons/crm_lead_code/tests/__init__.py
odoo_addons/crm_lead_code/tests/test_crm_lead_code.py
odoo_addons/crm_lead_code/views/crm_lead_view.xml
odoo8_addon_crm_lead_code-8.0.1.0.0.99.dev17.dist-info/METADATA
odoo8_addon_crm_lead_code-8.0.1.0.0.99.dev17.dist-info/WHEEL
odoo8_addon_crm_lead_code-8.0.1.0.0.99.dev17.dist-info/namespace_packages.txt
odoo8_addon_crm_lead_code-8.0.1.0.0.99.dev17.dist-info/top_level.txt
odoo8_addon_crm_lead_code-8.0.1.0.0.99.dev17.dist-info/RECORD
